tests/__init__.py
tests/test.py
tgemoji/__init__.py
tgemoji/converttools.py
tgemoji/preprocess.py
tgemoji-1.0.1.dist-info/LICENSE
tgemoji-1.0.1.dist-info/METADATA
tgemoji-1.0.1.dist-info/WHEEL
tgemoji-1.0.1.dist-info/top_level.txt
tgemoji-1.0.1.dist-info/RECORD
