Metadata-Version: 2.1
Name: tgemoji
Version: 1.0.1
Summary: Collection of text formatting utils for Telegram related libraries
Home-page: https://github.com/yourusername/your_library
Author: TurboPerdak
Author-email: yarikvodila52@gmail.com
Classifier: Programming Language :: Python :: 3
Classifier: License :: OSI Approved :: MIT License
Classifier: Operating System :: OS Independent
Requires-Python: >=3.6
License-File: LICENSE
